{
  "version": 1,
  "generatedAt": "2026-07-09T13:48:56.650Z",
  "byPath": {
    "wiki/analyses/2026-07-09-analisi-conformita-opentds-al-regolamento-ipsc-handgun-2024.md": {
      "inbound": [
        "wiki/syntheses/opentds-ipsc-compliance.md"
      ],
      "outbound": [
        "wiki/concepts/ipsc-divisions.md",
        "wiki/concepts/ipsc-penalties.md",
        "wiki/concepts/ipsc-range-commands.md",
        "wiki/concepts/ipsc-safety-rules.md",
        "wiki/concepts/ipsc-scoring.md",
        "wiki/concepts/ipsc-stage-design.md",
        "wiki/concepts/ipsc-targets.md",
        "wiki/entities/ipsc.md",
        "wiki/sources/SRC-2026-07-09-001.md",
        "wiki/syntheses/opentds-ipsc-compliance.md"
      ]
    },
    "wiki/concepts/ipsc-divisions.md": {
      "inbound": [
        "wiki/analyses/2026-07-09-analisi-conformita-opentds-al-regolamento-ipsc-handgun-2024.md",
        "wiki/concepts/ipsc-scoring.md",
        "wiki/entities/ipsc.md",
        "wiki/sources/SRC-2026-07-09-001.md",
        "wiki/syntheses/opentds-ipsc-compliance.md"
      ],
      "outbound": [
        "wiki/concepts/ipsc-safety-rules.md",
        "wiki/concepts/ipsc-scoring.md",
        "wiki/concepts/ipsc-targets.md",
        "wiki/sources/SRC-2026-07-09-001.md",
        "wiki/syntheses/opentds-ipsc-compliance.md"
      ]
    },
    "wiki/concepts/ipsc-penalties.md": {
      "inbound": [
        "wiki/analyses/2026-07-09-analisi-conformita-opentds-al-regolamento-ipsc-handgun-2024.md",
        "wiki/concepts/ipsc-range-commands.md",
        "wiki/concepts/ipsc-safety-rules.md",
        "wiki/concepts/ipsc-scoring.md",
        "wiki/concepts/ipsc-stage-design.md",
        "wiki/concepts/ipsc-targets.md",
        "wiki/sources/SRC-2026-07-09-001.md",
        "wiki/syntheses/opentds-ipsc-compliance.md"
      ],
      "outbound": [
        "wiki/concepts/ipsc-range-commands.md",
        "wiki/concepts/ipsc-safety-rules.md",
        "wiki/concepts/ipsc-scoring.md",
        "wiki/concepts/ipsc-stage-design.md",
        "wiki/sources/SRC-2026-07-09-001.md"
      ]
    },
    "wiki/concepts/ipsc-range-commands.md": {
      "inbound": [
        "wiki/analyses/2026-07-09-analisi-conformita-opentds-al-regolamento-ipsc-handgun-2024.md",
        "wiki/concepts/ipsc-penalties.md",
        "wiki/concepts/ipsc-safety-rules.md",
        "wiki/sources/SRC-2026-07-09-001.md",
        "wiki/syntheses/opentds-ipsc-compliance.md"
      ],
      "outbound": [
        "wiki/concepts/ipsc-penalties.md",
        "wiki/concepts/ipsc-safety-rules.md",
        "wiki/concepts/ipsc-stage-design.md",
        "wiki/entities/ipsc.md",
        "wiki/sources/SRC-2026-07-09-001.md"
      ]
    },
    "wiki/concepts/ipsc-safety-rules.md": {
      "inbound": [
        "wiki/analyses/2026-07-09-analisi-conformita-opentds-al-regolamento-ipsc-handgun-2024.md",
        "wiki/concepts/ipsc-divisions.md",
        "wiki/concepts/ipsc-penalties.md",
        "wiki/concepts/ipsc-range-commands.md",
        "wiki/concepts/ipsc-stage-design.md",
        "wiki/entities/ipsc.md",
        "wiki/sources/SRC-2026-07-09-001.md",
        "wiki/syntheses/opentds-ipsc-compliance.md"
      ],
      "outbound": [
        "wiki/concepts/ipsc-penalties.md",
        "wiki/concepts/ipsc-range-commands.md",
        "wiki/concepts/ipsc-stage-design.md",
        "wiki/entities/ipsc.md",
        "wiki/sources/SRC-2026-07-09-001.md"
      ]
    },
    "wiki/concepts/ipsc-scoring.md": {
      "inbound": [
        "wiki/analyses/2026-07-09-analisi-conformita-opentds-al-regolamento-ipsc-handgun-2024.md",
        "wiki/concepts/ipsc-divisions.md",
        "wiki/concepts/ipsc-penalties.md",
        "wiki/concepts/ipsc-stage-design.md",
        "wiki/concepts/ipsc-targets.md",
        "wiki/entities/ipsc.md",
        "wiki/sources/SRC-2026-07-09-001.md",
        "wiki/syntheses/opentds-ipsc-compliance.md"
      ],
      "outbound": [
        "wiki/concepts/ipsc-divisions.md",
        "wiki/concepts/ipsc-penalties.md",
        "wiki/concepts/ipsc-stage-design.md",
        "wiki/concepts/ipsc-targets.md",
        "wiki/sources/SRC-2026-07-09-001.md",
        "wiki/syntheses/opentds-ipsc-compliance.md"
      ]
    },
    "wiki/concepts/ipsc-stage-design.md": {
      "inbound": [
        "wiki/analyses/2026-07-09-analisi-conformita-opentds-al-regolamento-ipsc-handgun-2024.md",
        "wiki/concepts/ipsc-penalties.md",
        "wiki/concepts/ipsc-range-commands.md",
        "wiki/concepts/ipsc-safety-rules.md",
        "wiki/concepts/ipsc-scoring.md",
        "wiki/concepts/ipsc-targets.md",
        "wiki/entities/ipsc.md",
        "wiki/sources/SRC-2026-07-09-001.md",
        "wiki/syntheses/opentds-ipsc-compliance.md"
      ],
      "outbound": [
        "wiki/concepts/ipsc-penalties.md",
        "wiki/concepts/ipsc-safety-rules.md",
        "wiki/concepts/ipsc-scoring.md",
        "wiki/concepts/ipsc-targets.md",
        "wiki/sources/SRC-2026-07-09-001.md",
        "wiki/syntheses/opentds-ipsc-compliance.md"
      ]
    },
    "wiki/concepts/ipsc-targets.md": {
      "inbound": [
        "wiki/analyses/2026-07-09-analisi-conformita-opentds-al-regolamento-ipsc-handgun-2024.md",
        "wiki/concepts/ipsc-divisions.md",
        "wiki/concepts/ipsc-scoring.md",
        "wiki/concepts/ipsc-stage-design.md",
        "wiki/sources/SRC-2026-07-09-001.md",
        "wiki/syntheses/opentds-ipsc-compliance.md"
      ],
      "outbound": [
        "wiki/concepts/ipsc-penalties.md",
        "wiki/concepts/ipsc-scoring.md",
        "wiki/concepts/ipsc-stage-design.md",
        "wiki/sources/SRC-2026-07-09-001.md",
        "wiki/syntheses/opentds-ipsc-compliance.md"
      ]
    },
    "wiki/entities/fitds.md": {
      "inbound": [
        "wiki/entities/ipsc.md",
        "wiki/entities/iroa.md",
        "wiki/sources/SRC-2026-07-09-001.md",
        "wiki/syntheses/opentds-ipsc-compliance.md"
      ],
      "outbound": [
        "wiki/entities/ipsc.md",
        "wiki/entities/iroa.md",
        "wiki/sources/SRC-2026-07-09-001.md"
      ]
    },
    "wiki/entities/ipsc.md": {
      "inbound": [
        "wiki/analyses/2026-07-09-analisi-conformita-opentds-al-regolamento-ipsc-handgun-2024.md",
        "wiki/concepts/ipsc-range-commands.md",
        "wiki/concepts/ipsc-safety-rules.md",
        "wiki/entities/fitds.md",
        "wiki/entities/iroa.md",
        "wiki/sources/SRC-2026-07-09-001.md",
        "wiki/syntheses/opentds-ipsc-compliance.md"
      ],
      "outbound": [
        "wiki/concepts/ipsc-divisions.md",
        "wiki/concepts/ipsc-safety-rules.md",
        "wiki/concepts/ipsc-scoring.md",
        "wiki/concepts/ipsc-stage-design.md",
        "wiki/entities/fitds.md",
        "wiki/entities/iroa.md",
        "wiki/sources/SRC-2026-07-09-001.md"
      ]
    },
    "wiki/entities/iroa.md": {
      "inbound": [
        "wiki/entities/fitds.md",
        "wiki/entities/ipsc.md",
        "wiki/sources/SRC-2026-07-09-001.md"
      ],
      "outbound": [
        "wiki/entities/fitds.md",
        "wiki/entities/ipsc.md",
        "wiki/sources/SRC-2026-07-09-001.md"
      ]
    },
    "wiki/sources/SRC-2026-07-09-001.md": {
      "inbound": [
        "wiki/analyses/2026-07-09-analisi-conformita-opentds-al-regolamento-ipsc-handgun-2024.md",
        "wiki/concepts/ipsc-divisions.md",
        "wiki/concepts/ipsc-penalties.md",
        "wiki/concepts/ipsc-range-commands.md",
        "wiki/concepts/ipsc-safety-rules.md",
        "wiki/concepts/ipsc-scoring.md",
        "wiki/concepts/ipsc-stage-design.md",
        "wiki/concepts/ipsc-targets.md",
        "wiki/entities/fitds.md",
        "wiki/entities/ipsc.md",
        "wiki/entities/iroa.md",
        "wiki/sources/SRC-2026-07-09-001.md",
        "wiki/syntheses/opentds-ipsc-compliance.md"
      ],
      "outbound": [
        "wiki/concepts/ipsc-divisions.md",
        "wiki/concepts/ipsc-penalties.md",
        "wiki/concepts/ipsc-range-commands.md",
        "wiki/concepts/ipsc-safety-rules.md",
        "wiki/concepts/ipsc-scoring.md",
        "wiki/concepts/ipsc-stage-design.md",
        "wiki/concepts/ipsc-targets.md",
        "wiki/entities/fitds.md",
        "wiki/entities/ipsc.md",
        "wiki/entities/iroa.md",
        "wiki/sources/SRC-2026-07-09-001.md",
        "wiki/syntheses/opentds-ipsc-compliance.md"
      ]
    },
    "wiki/syntheses/opentds-ipsc-compliance.md": {
      "inbound": [
        "wiki/analyses/2026-07-09-analisi-conformita-opentds-al-regolamento-ipsc-handgun-2024.md",
        "wiki/concepts/ipsc-divisions.md",
        "wiki/concepts/ipsc-scoring.md",
        "wiki/concepts/ipsc-stage-design.md",
        "wiki/concepts/ipsc-targets.md",
        "wiki/sources/SRC-2026-07-09-001.md"
      ],
      "outbound": [
        "wiki/analyses/2026-07-09-analisi-conformita-opentds-al-regolamento-ipsc-handgun-2024.md",
        "wiki/concepts/ipsc-divisions.md",
        "wiki/concepts/ipsc-penalties.md",
        "wiki/concepts/ipsc-range-commands.md",
        "wiki/concepts/ipsc-safety-rules.md",
        "wiki/concepts/ipsc-scoring.md",
        "wiki/concepts/ipsc-stage-design.md",
        "wiki/concepts/ipsc-targets.md",
        "wiki/entities/fitds.md",
        "wiki/entities/ipsc.md",
        "wiki/sources/SRC-2026-07-09-001.md"
      ]
    }
  }
}
